{
  "parent": "minecraft:recipes/root",
  "criteria": {
    "has_stacked_raw_copper_blocks": {
      "conditions": {
        "items": [
          {
            "items": "stackedblocksfarmersdelight-port:stacked_raw_copper_blocks"
          }
        ]
      },
      "trigger": "minecraft:inventory_changed"
    },
    "has_the_recipe": {
      "conditions": {
        "recipe": "stackedblocksfarmersdelight-port:stacked_raw_copper_blocks_to_raw_copper"
      },
      "trigger": "minecraft:recipe_unlocked"
    }
  },
  "requirements": [
    [
      "has_the_recipe",
      "has_stacked_raw_copper_blocks"
    ]
  ],
  "rewards": {
    "recipes": [
      "stackedblocksfarmersdelight-port:stacked_raw_copper_blocks_to_raw_copper"
    ]
  }
}